{"compressionlevel":-1,"height":9,"infinite":false,"layers":[{"height":9,"id":1,"name":"Collision 0","opacity":1,"type":"tilelayer","visible":true,"width":9,"x":0,"y":0,"sparsed":[0,2,1,2,2,2,3,2,4,2,5,2,6,2,7,2,8,2,9,2,17,2,72,2,73,2,74,2,75,2,76,2,77,2,78,2,79,2,80,2]},{"height":9,"id":3,"name":"Collision 1","opacity":1,"type":"tilelayer","visible":true,"width":9,"x":0,"y":0,"sparsed":[]},{"height":9,"id":4,"name":"Collision 2","opacity":1,"type":"tilelayer","visible":true,"width":9,"x":0,"y":0,"sparsed":[]},{"draworder":"topdown","id":2,"name":"objects","objects":[{"height":0,"id":1,"name":"player-start","point":true,"rotation":0,"type":"player-start","visible":true,"width":0,"x":144,"y":256},{"gid":2,"height":32,"id":6,"name":"ring","rotation":0,"type":"ring","visible":true,"width":32,"x":0,"y":176},{"gid":2,"height":32,"id":7,"name":"ring","rotation":0,"type":"ring","visible":true,"width":32,"x":32,"y":176},{"gid":2,"height":32,"id":8,"name":"ring","rotation":0,"type":"ring","visible":true,"width":32,"x":64,"y":176},{"gid":2,"height":32,"id":9,"name":"ring","rotation":0,"type":"ring","visible":true,"width":32,"x":96,"y":176},{"gid":2,"height":40,"id":22,"name":"drop-cage","properties":[{"name":"waitFor","type":"object","value":24}],"rotation":0,"type":"drop-cage","visible":true,"width":48,"x":152,"y":192},{"gid":2,"height":32,"id":23,"name":"sheild-normal-monitor","properties":[{"name":"static","type":"bool","value":false}],"rotation":0,"type":"sheild-normal-monitor","visible":true,"width":32,"x":160,"y":256},{"gid":2,"height":32,"id":24,"name":"slot-machine","rotation":0,"type":"slot-machine","visible":true,"width":96,"x":128,"y":136},{"gid":2,"height":32,"id":25,"name":"emblem","rotation":0,"type":"emblem","visible":true,"width":32,"x":48,"y":112}],"opacity":1,"type":"objectgroup","visible":true,"x":0,"y":0},{"draworder":"topdown","id":5,"name":"regions","objects":[{"gid":2,"height":288,"id":4,"name":"loading-region","properties":[{"name":"map","type":"string","value":"/map/cell.json"},{"name":"xOffset","type":"int","value":2},{"name":"yOffset","type":"int","value":0}],"rotation":0,"type":"loading-region","visible":true,"width":64,"x":224,"y":288}],"opacity":1,"type":"objectgroup","visible":true,"x":0,"y":0}],"nextlayerid":6,"nextobjectid":26,"orientation":"orthogonal","renderorder":"right-down","tiledversion":"1.7.1","tileheight":32,"tilesets":[{"columns":22,"firstgid":1,"image":"shapes.png","imageheight":256,"imagewidth":704,"margin":0,"name":"shapes","spacing":0,"tilecount":176,"tileheight":32,"tilewidth":32}],"tilewidth":32,"type":"map","version":"1.6","width":9}